setup.py
cofre/__init__.py
cofre/core.py
cofre/errors.py
cofre/simplesecure.py
cofre/store.py
cofre.egg-info/PKG-INFO
cofre.egg-info/SOURCES.txt
cofre.egg-info/dependency_links.txt
cofre.egg-info/requires.txt
cofre.egg-info/top_level.txt
scripts/cofre