Metadata-Version: 1.0
Name: cofre
Version: 0.2.5
Summary: the serendipitous password manager
Home-page: https://github.com/rferreira/cofre
Author: Rafael Ferreira
Author-email: raf@ophion.org
License: MIT/X11
Keywords: password encryption rsa
Platform: UNKNOWN
Classifier: Development Status :: 4 - Beta
Classifier: Topic :: Utilities
Classifier: License :: OSI Approved :: Apache Software License
